{
  "dishes": [
    "Aedviljatoit",
    "Antipasto",
    "Austrikaste",
    "Bambusevõrsed",
    "Basturma",
    "Bergamo",
    "Brescia",
    "Como",
    "Cremona",
    "Dolma",
    "Halvaa",
    "Harissa",
    "Hašš",
    "Hiina nuudlid",
    "Horovats",
    "Ingver",
    "Ishkhan",
    "Itaalia juust",
    "Itaalia kalaroad",
    "Itaalia kohv",
    "Itaalia leivatooted",
    "Itaalia liharoad",
    "Itaalia magustoidud ja küpsetised",
    "Itaalia riisiroad",
    "Itaalia supid ja kastmed",
    "Itaalia vein",
    "Jajik",
    "Joogid",
    "Juust",
    "Kala",
    "Kalatoit",
    "Kohv",
    "Koriander",
    "Levinumad pizzad",
    "Liha",
    "Liiliapungad",
    "Magustoit",
    "Mango",
    "Mantua",
    "Milano",
    "Munatoit",
    "Musaka",
    "Oapastad",
    "Pahlava",
    "Pasta",
    "Pavia",
    "Piimatooted",
    "Pita",
    "Porrulauk",
    "Puuvili",
    "Riis",
    "Riisiäädikas",
    "Riisivein",
    "Salat",
    "Seesamiõli",
    "Seesamiseemned",
    "Sichuani pipar ehk fagara",
    "Soe või külm lihatoit",
    "Sojaidud",
    "Sojakaste",
    "Sondrio",
    "Tähtaniis",
    "Tofu",
    "Tšilliõli",
    "Tšillipasta",
    "Üks",
    "Väikesed külmad suupistedigale inimesele eraldi asetatud toidurühmakesena",
    "Vesikastanid ehk vesialss",
    "Viievürtsisegu"
  ],
  "drinks": [
    "Amaretto",
    "Amarula",
    "Aniisiviin",
    "Aperitiiv",
    "Arak",
    "Ararat",
    "Ayahuasca",
    "Baileys",
    "Brändi",
    "BrewDog",
    "Campari",
    "Chinchón",
    "Coca-Cola",
    "Cointreau",
    "Dynami:t",
    "Fanta",
    "Handsa",
    "Hapupiim",
    "Hapurokk",
    "Julep",
    "Kaeratumm",
    "Kahlúa",
    "Kakao",
    "Kali",
    "Kanepipiim",
    "Karastusjook",
    "Kelluke",
    "Kelt",
    "Kilikia",
    "Klarett",
    "Kofeiinitustamine",
    "Kokteil",
    "Kotayk",
    "Kumõss",
    "Licor 43",
    "Liköör",
    "Limonaad",
    "Limoncello",
    "Mahl",
    "Martini",
    "Mate",
    "Mõdu",
    "Mote con huesillo",
    "Must kohv",
    "Oghid",
    "Õlu",
    "Pepsi",
    "Piim",
    "Pirita ürdiliköör",
    "Punsli õli",
    "Raki",
    "Rakija",
    "RC Cola",
    "Red Bull",
    "Roheline draakon",
    "Sake",
    "Šerri",
    "Shōchū",
    "Siider",
    "Spritz",
    "Taar",
    "Tarhun",
    "Toonik",
    "Triple sec",
    "Tsípouro",
    "Unicum",
    "Vein",
    "Vermut",
    "Viinamonopol",
    "Viljakohv"
  ],
  "fruits": [
    "Aiva ehk küdoonia",
    "Alõtša",
    "Apelsin",
    "Aprikoos",
    "Avokaado",
    "Bilimbi",
    "Dattel",
    "Granaatõun",
    "Greip",
    "Guajaav",
    "Hurmaa",
    "Kiivi",
    "Kirss",
    "Hapukirss",
    "Murel",
    "Maguskirss",
    "Karamboola ehk tähtvili",
    "Kerimoia ehk suhkruannoona",
    "Kinkan ehk kumkvaat",
    "Klementiin",
    "Kreek",
    "Laim",
    "Hapulaim",
    "Maguslaim",
    "Litši",
    "Mandariin",
    "Mango",
    "Mangostan",
    "Nektariin",
    "Oliiv",
    "Õun",
    "Papaia",
    "Persimon",
    "Pirn",
    "Ploom",
    "Pomel ehk pompelmuus",
    "Rambutan",
    "Sidrun",
    "Sviiti",
    "Tamarillo",
    "Viigimari ehk viik",
    "Viinamari",
    "Virsik",
    "Lamevirsik"
  ],
  "spices": [
    "Aniis",
    "Annatto",
    "Cayenne'i pipar",
    "Fenugreek",
    "Feerulavaik ehk juudavaik",
    "Granaatõunaseemned",
    "Ingver",
    "Kadakamarjad",
    "Kaneel",
    "Kappar",
    "Kardemon",
    "Karusköömen ehk ajowan",
    "Kassia ehk hiina kaneel",
    "Keedusool",
    "Koriander",
    "Kurkum",
    "Loorber",
    "Mooniseemned",
    "Muskaat",
    "Nelk",
    "Nigella ehk aed-mustköömen",
    "Paprikapulber",
    "Pipar",
    "Ristiköömen",
    "Roheline pipar",
    "Safran",
    "Seesamiseemned",
    "Selleriseemned",
    "Sichuani pipar",
    "Sinepiseemned",
    "Sool",
    "Tamarind",
    "Tähtaniis",
    "Vanill",
    "Vürts ehk piment",
    "Vürtsköömen"
  ],
  "vegetables": [
    "Aed-mustjuur",
    "Aed-piimjuur",
    "Aedportulak",
    "Aeduba",
    "Apteegitill",
    "Artišokk",
    "Avokaado",
    "Baklažaan",
    "Bambusevõrsed",
    "Bataat",
    "Brokoli",
    "Ehk",
    "Ehk",
    "Füüsal",
    "Hapuoblikas",
    "Harilik paprika",
    "Hernes",
    "Hiina kapsas",
    "Itaalia lillnaeris",
    "Jaapani redis",
    "Jamss",
    "Juurseller",
    "Kaalikas",
    "Kabatšokk",
    "Kartul",
    "Kibepipar",
    "Kikerhernes",
    "Kõrvits",
    "Kurk",
    "Lehtkapsas",
    "Lehtpeet",
    "Lillkapsas",
    "Maapirn",
    "Maniokk",
    "Mugulpäevalill",
    "Murulauk,küüslauk",
    "Muskushibisk",
    "Must rõigas",
    "Naeris",
    "Nuikapsas",
    "Okra",
    "Pastinaak",
    "Peakapsas",
    "Peet",
    "Pesasibul",
    "Petersell",
    "Põld-võõrkapsas",
    "Põldkännak",
    "Põlduba",
    "Porgand",
    "Porrulauk",
    "Punasigur",
    "Rabarber",
    "Redis",
    "Rooskapsas",
    "Rukola",
    "Salat",
    "Salatkress",
    "Salatsigur",
    "Sibul",
    "Sigur",
    "Sojauba",
    "Söödav",
    "Söödav",
    "Spargel",
    "Spinat",
    "Suhkruhernes",
    "Takjas",
    "Talisibul",
    "Taro",
    "Till",
    "Tomat",
    "Tsukiini",
    "Ubajuur",
    "Varsseller"
  ]
}
