{
  "day": {
    "name": [
      "星期一",
      "星期二",
      "星期三",
      "星期四",
      "星期五",
      "星期六",
      "星期日"
    ],
    "abbr": [
      "一",
      "二",
      "三",
      "四",
      "五",
      "六",
      "日"
    ]
  },
  "formats": {
    "date": "%Y-%m-%d",
    "time": "%H:%M:%S"
  },
  "month": {
    "name": [
      "一月",
      "二月",
      "三月",
      "四月",
      "五月",
      "六月",
      "七月",
      "八月",
      "九月",
      "十月",
      "十一月",
      "十二月"
    ],
    "abbr": [
      "一月",
      "二月",
      "三月",
      "四月",
      "五月",
      "六月",
      "七月",
      "八月",
      "九月",
      "十月",
      "十一月",
      "十二月"
    ]
  },
  "periodicity": [
    "一直",
    "通常",
    "经常",
    "有时",
    "很少",
    "几乎不",
    "从不"
  ]
}
